ma_gym/__init__.py
ma_gym/envs/__init__.py
ma_gym/envs/checkers/__init__.py
ma_gym/envs/checkers/checkers.py
ma_gym/envs/combat/__init__.py
ma_gym/envs/combat/combat.py
ma_gym/envs/lumberjacks/__init__.py
ma_gym/envs/lumberjacks/lumberjacks.py
ma_gym/envs/openai/__init__.py
ma_gym/envs/pong_duel/__init__.py
ma_gym/envs/pong_duel/pong_duel.py
ma_gym/envs/predator_prey/__init__.py
ma_gym/envs/predator_prey/predator_prey.py
ma_gym/envs/switch/__init__.py
ma_gym/envs/switch/switch_one_corridor.py
ma_gym/envs/traffic_junction/__init__.py
ma_gym/envs/traffic_junction/traffic_junction.py
ma_gym/envs/utils/__init__.py
ma_gym/envs/utils/action_space.py
ma_gym/envs/utils/draw.py
ma_gym/envs/utils/observation_space.py
ma_gym/wrappers/__init__.py
ma_gym/wrappers/monitor.py
ma_gym/wrappers/monitoring/__init__.py
ma_gym/wrappers/monitoring/stats_recorder.py
tests/__init__.py
tests/envs/__init__.py
tests/envs/test_checkers.py
tests/envs/test_combat.py
tests/envs/test_lumberjacks.py
tests/envs/test_openai_cartpole.py
tests/envs/test_pong_duel.py
tests/envs/test_predatorprey5x5.py
tests/envs/test_predatorprey7x7.py
tests/envs/test_switch2.py
tests/envs/test_trafficjunction.py
ma_gym-0.0.14.dist-info/LICENSE
ma_gym-0.0.14.dist-info/METADATA
ma_gym-0.0.14.dist-info/WHEEL
ma_gym-0.0.14.dist-info/top_level.txt
ma_gym-0.0.14.dist-info/RECORD
