Metadata-Version: 2.1
Name: ma-gym
Version: 0.0.14
Summary: A collection of multi agent environments based on OpenAI gym.
Home-page: https://github.com/koulanurag/ma-gym
Author: Anurag Koul
Author-email: koulanurag@gmail.com
License: MIT License
Classifier: Programming Language :: Python :: 3.6
Classifier: Programming Language :: Python :: 3.7
Classifier: Programming Language :: Python :: 3.8
Classifier: Programming Language :: Python :: 3.9
Classifier: Programming Language :: Python :: 3.10
Classifier: Programming Language :: Python :: 3.11
Requires-Python: >=3.6, <3.12
Provides-Extra: test
Provides-Extra: develop
Provides-Extra: all
License-File: LICENSE
